enpyre/__init__.py
enpyre/core.py
enpyre/enpyre.py
enpyre/graphics.py
enpyre/js_interface.py
enpyre-0.0.6.dist-info/LICENSE
enpyre-0.0.6.dist-info/WHEEL
enpyre-0.0.6.dist-info/METADATA
enpyre-0.0.6.dist-info/RECORD
