Metadata-Version: 2.1
Name: enpyre
Version: 0.0.6
Summary: A Python game engine for the browser
Home-page: https://github.com/Enpyre/engine
License: MPL-2.0
Keywords: game,engine,python,browser
Author: Lucas Amoedo
Author-email: lucas.advc@gmail.com
Requires-Python: >=3.7,<4.0
Classifier: Development Status :: 2 - Pre-Alpha
Classifier: Environment :: Other Environment
Classifier: Environment :: Web Environment
Classifier: Intended Audience :: Education
Classifier: License :: OSI Approved
Classifier: License :: OSI Approved :: Mozilla Public License 2.0 (MPL 2.0)
Classifier: Programming Language :: Python :: 3
Classifier: Programming Language :: Python :: 3.10
Classifier: Programming Language :: Python :: 3.7
Classifier: Programming Language :: Python :: 3.8
Classifier: Programming Language :: Python :: 3.9
Classifier: Topic :: Education
Classifier: Topic :: Games/Entertainment
Project-URL: Repository, https://github.com/Enpyre/engine
